{"network": [{"name": "Armor", "icon": "armor.png", "alias": ""}, {"name": "CDN", "icon": "cdn.png", "alias": ""}, {"name": "DedicatedInterconnect", "icon": "dedicated-interconnect.png", "alias": ""}, {"name": "DNS", "icon": "dns.png", "alias": ""}, {"name": "ExternalIpAddresses", "icon": "external-ip-addresses.png", "alias": ""}, {"name": "FirewallRules", "icon": "firewall-rules.png", "alias": ""}, {"name": "LoadBalancing", "icon": "load-balancing.png", "alias": ""}, {"name": "NAT", "icon": "nat.png", "alias": ""}, {"name": "Network", "icon": "network.png", "alias": ""}, {"name": "PartnerInterconnect", "icon": "partner-interconnect.png", "alias": ""}, {"name": "PremiumNetworkTier", "icon": "premium-network-tier.png", "alias": ""}, {"name": "Router", "icon": "router.png", "alias": ""}, {"name": "Routes", "icon": "routes.png", "alias": ""}, {"name": "StandardNetworkTier", "icon": "standard-network-tier.png", "alias": ""}, {"name": "TrafficDirector", "icon": "traffic-director.png", "alias": ""}, {"name": "VirtualPrivateCloud", "icon": "virtual-private-cloud.png", "alias": "VPC"}, {"name": "VPN", "icon": "vpn.png", "alias": ""}], "ml": [{"name": "AdvancedSolutionsLab", "icon": "advanced-solutions-lab.png", "alias": ""}, {"name": "AIHub", "icon": "ai-hub.png", "alias": ""}, {"name": "AIPlatformDataLabelingService", "icon": "ai-platform-data-labeling-service.png", "alias": ""}, {"name": "AIPlatform", "icon": "ai-platform.png", "alias": ""}, {"name": "AutomlNaturalLanguage", "icon": "automl-natural-language.png", "alias": ""}, {"name": "AutomlTables", "icon": "automl-tables.png", "alias": ""}, {"name": "AutomlTranslation", "icon": "automl-translation.png", "alias": ""}, {"name": "AutomlVideoIntelligence", "icon": "automl-video-intelligence.png", "alias": ""}, {"name": "AutomlVision", "icon": "automl-vision.png", "alias": ""}, {"name": "Automl", "icon": "automl.png", "alias": "AutoML"}, {"name": "DialogFlowEnterpriseEdition", "icon": "dialog-flow-enterprise-edition.png", "alias": ""}, {"name": "InferenceAPI", "icon": "inference-api.png", "alias": ""}, {"name": "JobsAPI", "icon": "jobs-api.png", "alias": ""}, {"name": "NaturalLanguageAPI", "icon": "natural-language-api.png", "alias": "NLAPI"}, {"name": "RecommendationsAI", "icon": "recommendations-ai.png", "alias": ""}, {"name": "SpeechToText", "icon": "speech-to-text.png", "alias": "STT"}, {"name": "TextToSpeech", "icon": "text-to-speech.png", "alias": "TTS"}, {"name": "TPU", "icon": "tpu.png", "alias": ""}, {"name": "TranslationAPI", "icon": "translation-api.png", "alias": ""}, {"name": "VideoIntelligenceAPI", "icon": "video-intelligence-api.png", "alias": ""}, {"name": "VisionAPI", "icon": "vision-api.png", "alias": ""}], "security": [{"name": "Iam", "icon": "iam.png", "alias": ""}, {"name": "IAP", "icon": "iap.png", "alias": ""}, {"name": "KeyManagementService", "icon": "key-management-service.png", "alias": "KMS"}, {"name": "ResourceManager", "icon": "resource-manager.png", "alias": ""}, {"name": "SecurityCommandCenter", "icon": "security-command-center.png", "alias": "SCC"}, {"name": "SecurityScanner", "icon": "security-scanner.png", "alias": ""}], "devtools": [{"name": "Build", "icon": "build.png", "alias": ""}, {"name": "CodeForIntellij", "icon": "code-for-intellij.png", "alias": ""}, {"name": "Code", "icon": "code.png", "alias": ""}, {"name": "ContainerRegistry", "icon": "container-registry.png", "alias": "GCR"}, {"name": "GradleAppEnginePlugin", "icon": "gradle-app-engine-plugin.png", "alias": ""}, {"name": "IdePlugins", "icon": "ide-plugins.png", "alias": ""}, {"name": "MavenAppEnginePlugin", "icon": "maven-app-engine-plugin.png", "alias": ""}, {"name": "Scheduler", "icon": "scheduler.png", "alias": ""}, {"name": "SDK", "icon": "sdk.png", "alias": ""}, {"name": "SourceRepositories", "icon": "source-repositories.png", "alias": ""}, {"name": "Tasks", "icon": "tasks.png", "alias": ""}, {"name": "TestLab", "icon": "test-lab.png", "alias": ""}, {"name": "ToolsForEclipse", "icon": "tools-for-eclipse.png", "alias": ""}, {"name": "ToolsForPowershell", "icon": "tools-for-powershell.png", "alias": ""}, {"name": "ToolsForVisualStudio", "icon": "tools-for-visual-studio.png", "alias": ""}], "iot": [{"name": "IotCore", "icon": "iot-core.png", "alias": ""}], "database": [{"name": "Bigtable", "icon": "bigtable.png", "alias": "BigTable"}, {"name": "Datastore", "icon": "datastore.png", "alias": ""}, {"name": "Firestore", "icon": "firestore.png", "alias": ""}, {"name": "Memorystore", "icon": "memorystore.png", "alias": ""}, {"name": "Spanner", "icon": "spanner.png", "alias": ""}, {"name": "SQL", "icon": "sql.png", "alias": ""}], "compute": [{"name": "AppEngine", "icon": "app-engine.png", "alias": "GAE"}, {"name": "ComputeEngine", "icon": "compute-engine.png", "alias": "GCE"}, {"name": "ContainerOptimizedOS", "icon": "container-optimized-os.png", "alias": ""}, {"name": "Functions", "icon": "functions.png", "alias": "GCF"}, {"name": "GKEOnPrem", "icon": "gke-on-prem.png", "alias": ""}, {"name": "GPU", "icon": "gpu.png", "alias": ""}, {"name": "KubernetesEngine", "icon": "kubernetes-engine.png", "alias": "GKE"}, {"name": "Run", "icon": "run.png", "alias": ""}], "api": [{"name": "APIGateway", "icon": "api-gateway.png", "alias": ""}, {"name": "Endpoints", "icon": "endpoints.png", "alias": ""}], "analytics": [{"name": "Bigquery", "icon": "bigquery.png", "alias": "BigQuery"}, {"name": "Composer", "icon": "composer.png", "alias": ""}, {"name": "DataCatalog", "icon": "data-catalog.png", "alias": ""}, {"name": "DataFusion", "icon": "data-fusion.png", "alias": ""}, {"name": "Dataflow", "icon": "dataflow.png", "alias": ""}, {"name": "Datalab", "icon": "datalab.png", "alias": ""}, {"name": "Dataprep", "icon": "dataprep.png", "alias": ""}, {"name": "Dataproc", "icon": "dataproc.png", "alias": ""}, {"name": "Genomics", "icon": "genomics.png", "alias": ""}, {"name": "Pubsub", "icon": "pubsub.png", "alias": "PubSub"}], "migration": [{"name": "TransferAppliance", "icon": "transfer-appliance.png", "alias": ""}], "storage": [{"name": "Filestore", "icon": "filestore.png", "alias": ""}, {"name": "PersistentDisk", "icon": "persistent-disk.png", "alias": ""}, {"name": "Storage", "icon": "storage.png", "alias": "GCS"}], "operations": [{"name": "Monitoring", "icon": "monitoring.png", "alias": ""}]}