{"language": [{"name": "Bash", "icon": "bash.png", "alias": ""}, {"name": "C", "icon": "c.png", "alias": ""}, {"name": "Cpp", "icon": "cpp.png", "alias": ""}, {"name": "Csharp", "icon": "csharp.png", "alias": ""}, {"name": "Dart", "icon": "dart.png", "alias": ""}, {"name": "Elixir", "icon": "elixir.png", "alias": ""}, {"name": "Erlang", "icon": "erlang.png", "alias": ""}, {"name": "Go", "icon": "go.png", "alias": ""}, {"name": "Java", "icon": "java.png", "alias": ""}, {"name": "Javascript", "icon": "javascript.png", "alias": "JavaScript"}, {"name": "Kotlin", "icon": "kotlin.png", "alias": ""}, {"name": "Latex", "icon": "latex.png", "alias": ""}, {"name": "Matlab", "icon": "matlab.png", "alias": ""}, {"name": "Nodejs", "icon": "nodejs.png", "alias": "NodeJS"}, {"name": "Php", "icon": "php.png", "alias": "PHP"}, {"name": "Python", "icon": "python.png", "alias": ""}, {"name": "R", "icon": "r.png", "alias": ""}, {"name": "Ruby", "icon": "ruby.png", "alias": ""}, {"name": "Rust", "icon": "rust.png", "alias": ""}, {"name": "Scala", "icon": "scala.png", "alias": ""}, {"name": "Swift", "icon": "swift.png", "alias": ""}, {"name": "Typescript", "icon": "typescript.png", "alias": "TypeScript"}], "runtime": [{"name": "Dapr", "icon": "dapr.png", "alias": ""}], "flowchart": [{"name": "Action", "icon": "action.png", "alias": ""}, {"name": "Collate", "icon": "collate.png", "alias": ""}, {"name": "Database", "icon": "database.png", "alias": ""}, {"name": "Decision", "icon": "decision.png", "alias": ""}, {"name": "Delay", "icon": "delay.png", "alias": ""}, {"name": "Display", "icon": "display.png", "alias": ""}, {"name": "Document", "icon": "document.png", "alias": ""}, {"name": "InputOutput", "icon": "input-output.png", "alias": ""}, {"name": "Inspection", "icon": "inspection.png", "alias": ""}, {"name": "InternalStorage", "icon": "internal-storage.png", "alias": ""}, {"name": "LoopLimit", "icon": "loop-limit.png", "alias": ""}, {"name": "ManualInput", "icon": "manual-input.png", "alias": ""}, {"name": "ManualLoop", "icon": "manual-loop.png", "alias": ""}, {"name": "Merge", "icon": "merge.png", "alias": ""}, {"name": "MultipleDocuments", "icon": "multiple-documents.png", "alias": ""}, {"name": "OffPageConnectorLeft", "icon": "off-page-connector-left.png", "alias": ""}, {"name": "OffPageConnectorRight", "icon": "off-page-connector-right.png", "alias": ""}, {"name": "Or", "icon": "or.png", "alias": ""}, {"name": "PredefinedProcess", "icon": "predefined-process.png", "alias": ""}, {"name": "Preparation", "icon": "preparation.png", "alias": ""}, {"name": "Sort", "icon": "sort.png", "alias": ""}, {"name": "StartEnd", "icon": "start-end.png", "alias": ""}, {"name": "StoredData", "icon": "stored-data.png", "alias": ""}, {"name": "SummingJunction", "icon": "summing-junction.png", "alias": ""}], "framework": [{"name": "Angular", "icon": "angular.png", "alias": ""}, {"name": "Backbone", "icon": "backbone.png", "alias": ""}, {"name": "Django", "icon": "django.png", "alias": ""}, {"name": "Ember", "icon": "ember.png", "alias": ""}, {"name": "Fastapi", "icon": "fastapi.png", "alias": "FastAPI"}, {"name": "Flask", "icon": "flask.png", "alias": ""}, {"name": "Flutter", "icon": "flutter.png", "alias": ""}, {"name": "Laravel", "icon": "laravel.png", "alias": ""}, {"name": "Micronaut", "icon": "micronaut.png", "alias": ""}, {"name": "Rails", "icon": "rails.png", "alias": ""}, {"name": "React", "icon": "react.png", "alias": ""}, {"name": "Spring", "icon": "spring.png", "alias": ""}, {"name": "Starlette", "icon": "starlette.png", "alias": ""}, {"name": "Vue", "icon": "vue.png", "alias": ""}]}